{
  "scope": "C",
  "version": 2,
  "restricted": false,
  "overridable": true,
  "files": [
    "window.bin",
    "thumbnail.png"
  ],
  "attributes": {
    "lastModification": {
      "actor": "bduran",
      "timestamp": "2023-11-21T21:36:30Z"
    },
    "xml-format-version": 1,
    "parameter-names": "AdjSeq,AdjustTable,SelectedLineId,cpPLCWOCount,cpSelectedRunNum,cpSelectedWONum,cpSelectedWorkOrderAutoId",
    "lastModificationSignature": "cab5fe482b134c7957d0277fb77abffb4e3073fd853d53bb34d8f5bac68258c2"
  }
}